{
    "USA Ebay": {
        "URL_Part1": "https://www.ebay.com/sch/i.html?_from=R40&_nkw=\"",
        "URL_Part2": "\"&_sacat=0&rt=nc&LH_Sold=1&LH_Complete=1",
        "listings": "#srp-river-results > ul > li",
        "listingTitle": "div > div.s-item__info.clearfix > a > div > span",
        "listingPrice": "div > div.s-item__info.clearfix > div.s-item__details.clearfix > div:nth-child(1) > span > span"
    },
    "UK Ebay": {
        "URL_Part1": "https://www.ebay.co.uk/sch/i.html?_from=R40&_nkw=\"",
        "URL_Part2": "\"&_sacat=0&LH_TitleDesc=0&LH_PrefLoc=2&rt=nc&LH_Sold=1&LH_Complete=1",
        "listings": "#srp-river-results > ul > li",
        "listingTitle": "div > div.s-item__info.clearfix > a > div > span",
        "listingPrice": "div > div.s-item__info.clearfix > div.s-item__details.clearfix > div:nth-child(1) > span > span"
    },
    "CA Ebay": {
        "URL_Part1": "https://www.ebay.ca/sch/i.html?_from=R40&_nkw=\"",
        "URL_Part2": "\"&_sacat=0&LH_PrefLoc=2&rt=nc&LH_Sold=1&LH_Complete=1",
        "listings": "#srp-river-results > ul > li",
        "listingTitle": "div > div.s-item__info.clearfix > a > div > span",
        "listingPrice": "div > div.s-item__info.clearfix > div.s-item__details.clearfix > div:nth-child(1) > span > span"
    },
    "AU Ebay": {
        "URL_Part1": "https://www.ebay.com.au/sch/i.html?_from=R40&_nkw=\"",
        "URL_Part2": "\"&_sacat=0&LH_TitleDesc=0&LH_PrefLoc=2&rt=nc&LH_Sold=1&LH_Complete=1",
        "listings": "#srp-river-results > ul > li",
        "listingTitle": "div > div.s-item__info.clearfix > a > div > span",
        "listingPrice": "div > div.s-item__info.clearfix > div.s-item__details.clearfix > div:nth-child(1) > span > span"
    },
    "DE Ebay": {
        "URL_Part1": "https://www.ebay.de/sch/i.html?_from=R40&_nkw=\"",
        "URL_Part2": "\"&_sacat=0&rt=nc&LH_Sold=1&LH_Complete=1",
        "listings": "#srp-river-results > ul > li",
        "listingTitle": "div > div.s-item__info.clearfix > a > div > span",
        "listingPrice": "div > div.s-item__info.clearfix > div.s-item__details.clearfix > div:nth-child(1) > span > span"
    },
    "USA Newegg": {
        "URL_Part1": "https://www.newegg.com/p/pl?d=\"",
        "URL_Part2": "\"&N=601406709%20600030348%20600100181%20100007709&ComboBundle=true",
        "listings": "#app > div.page-content > section > div > div > div.row-body > div > div > div > div.row-body > div.row-body-inner > div > div.item-cells-wrap.border-cells.items-grid-view.four-cells.expulsion-one-cell > .item-cell",
        "listingTitle": ".item-info > .item-title",
        "listingPrice": ".item-action > ul > li.price-current > strong"
    },
    "CA Newegg": {
        "URL_Part1": "https://www.newegg.ca/p/pl?d=\"",
        "URL_Part2": "\"&N=600100181%20601406709%20600030348%20100007708&ComboBundle=true",
        "listings": "#app > div.page-content > section > div > div > div.row-body > div > div > div > div.row-body > div.row-body-inner > div > div.item-cells-wrap.border-cells.items-grid-view.four-cells.expulsion-one-cell > .item-cell",
        "listingTitle": ".item-info > .item-title",
        "listingPrice": ".item-action > ul > li.price-current > strong"
    },
    "US Amazon": {
        "URL_Part1": "https://www.amazon.com/s?k=\"",
        "URL_Part2": "\"&i=computers&rh=n%3A284822%2Cp_n_feature_browse-bin%3A23883927011%7C23883932011&dc&qid=1676656353&rnid=23883919011&ref=sr_nr_p_n_feature_browse-bin_1&ds=v1%3AF0U%2FLIw%2Fc%2BOoQK%2Fd64qbI97%2BzRc%2B1lrt30X56Z68BrQ",
        "listings": "div.sg-col-20-of-24",
        "listingTitle": "div:nth-child(1) > div:nth-child(1) > div:nth-child(1) > div:nth-child(2) > div:nth-child(1) > div:nth-child(1) > div:nth-child(1) > h2:nth-child(1) > a:nth-child(1) > span:nth-child(1)",
        "listingPrice": "div:nth-child(1) > div:nth-child(1) > div:nth-child(1) > div:nth-child(2) > div:nth-child(1) > div:nth-child(1) > div:nth-child(3) > div:nth-child(1) > div:nth-child(1) > div:nth-child(1) > div:nth-child(1) > a:nth-child(1) > span:nth-child(1) > span:nth-child(2) > span:nth-child(2)",
        "UseSelenium": true
    },
    "UK Amazon": {
        "URL_Part1": "https://www.amazon.co.uk/s?k=\"",
        "URL_Part2": "\"&i=computers&rh=n%3A430500031&dc&crid=P6D71N6ZOLP7&qid=1676667044&rnid=27399136031&sprefix=rtx+3050+%2Caps%2C174&ref=sr_nr_p_n_feature_thirteen_browse-bin_1&ds=v1%3AUEvHTbY5TxNRh9gy1pWYfcuP8lD1%2FRuYef9QgI2qCpU",
        "listings": "div.sg-col-20-of-24",
        "listingTitle": "div:nth-child(1) > div:nth-child(1) > div:nth-child(1) > div:nth-child(2) > div:nth-child(1) > div:nth-child(1) > div:nth-child(1) > h2:nth-child(1) > a:nth-child(1) > span:nth-child(1)",
        "listingPrice": "div:nth-child(1) > div:nth-child(1) > div:nth-child(1) > div:nth-child(2) > div:nth-child(1) > div:nth-child(1) > div:nth-child(3) > div:nth-child(1) > div:nth-child(1) > div:nth-child(1) > div:nth-child(1) > a:nth-child(1) > span:nth-child(1) > span:nth-child(2) > span:nth-child(2)",
        "UseSelenium": true
    }
}